Lab2/sourceCode/mux2_1.sv
module mux2_1(out, i0, i1, sel);
		output out;
		input i0, i1, sel;
		
		wire out1, out2, NOTsel;
		not n(NOTsel, sel);
		
		and a1(out1, i1, sel);
		and a2(out2, i0, NOTsel);
		or o(out, out1, out2);
endmodule

module mux2_1_testbench();
		reg i0, i1, sel;
		wire out;
		
		mux2_1 dut (.out, .i0, .i1, .sel);
		
		initial begin
				sel = 0; i0 = 0; i1 = 0; #10;
				sel = 0; i0 = 0; i1 = 1; #10;
				sel = 0; i0 = 1; i1 = 0; #10;
				sel = 0; i0 = 1; i1 = 1; #10;
				sel = 1; i0 = 0; i1 = 0; #10;
				sel = 1; i0 = 0; i1 = 1; #10;
				sel = 1; i0 = 1; i1 = 0; #10;
				sel = 1; i0 = 1; i1 = 1; #10;
		end
endmodule

Lab3/sourceCode/shiftll.v
// a barrel shifter to satisfy the single clock cycle constraint 
// and yet support the multibit shift operation
// @requires: A 32-bit data input, a 32-bit control input;
// @returns:  A 32-bit left shifted output to support shift by 7
module shiftll (busSLL, busA, sel);
	output [31:0] busSLL;
	input  [31:0] busA, sel;
	// output zSLL, oSLL, cSLL, nSLL;

	// wire carryOut;

	wire [31:0] Level1, Level2;

	genvar i, j, k;

	// 1-bit shift left
	mux2_1 m00(busSLL[0], Level1[0], 0, sel[0]);

	generate
		for(i = 1; i < 32; i = i+1) begin: Level0Loop
			mux2_1 m0x(busSLL[i], Level1[i], Level1[i-1], sel[0]);
		end
	endgenerate

	// 2-bit shift left
	mux2_1 m10(Level1[0], Level2[0], 0, sel[1]);
	mux2_1 m11(Level1[1], Level2[1], 0, sel[1]);

	generate
		for(j = 2; j < 32; j = j+1) begin: Level1Loop
			mux2_1 m1x(Level1[j], Level2[j], Level2[j-2], sel[1]);
		end
	endgenerate

	// 4-bit shift left
	mux2_1 m20(Level2[0], busA[0], 0, sel[2]);
	mux2_1 m21(Level2[1], busA[1], 0, sel[2]);
	mux2_1 m22(Level2[2], busA[2], 0, sel[2]);
	mux2_1 m23(Level2[3], busA[3], 0, sel[2]);

	generate
		for(k = 4; k < 32; k = k+1) begin: Level2Loop
			mux2_1 m2x(Level2[k], busA[k], busA[k-4], sel[2]);
		end
	endgenerate	

	// flag test(busSLL, busA, busB, carryOut, zSLL, oSLL, cSLL, nSLL);

endmodule

Lab3/sourceCode/tests/shiftllTest.v
`include "mux2_1.sv"
`include "shiftll.v"
module shiftllTest ();
	// localize variables
	wire [31:0] busADD;
	wire  [31:0] busA, busB;

	// declare an instance of the module
	shiftll shiftll (busADD, busA, busB);
	// Running the GUI part of simulation
	shiftlltester tester (busADD, busA, busB);

	// file for gtkwave

	initial
	begin
		$dumpfile("shiftlltest.vcd");
		$dumpvars(1, shiftll);
	end

endmodule

module shiftlltester (busADD, busA, busB);
	input [31:0] busADD;
	output reg  [31:0] busA, busB;

	parameter d = 20;
	initial // Response
	begin
		$display("busADD \t busA \t busB \t\t\t ");
		#d;
	end

	reg [31:0] i;
	initial // Stimulus
	begin
		$monitor("%b \t %b \t %b \t ", busADD, busA, busB, $time);
		busA = 32'h01010101; busB = 32'h00000001;
		#d;
		busA = 32'h01010101; busB = 32'h00000002;
		#d;
		busA = 32'h01010101; busB = 32'h00000003;
		#d;
		busA = 32'h01010101; busB = 32'h00000004;
		#d;
		busA = 32'h01010101; busB = 32'h00000005;
		#d;
		busA = 32'h01010101; busB = 32'h00000006;
		#d;
		busA = 32'h01010101; busB = 32'h00000007; 
		#d;
		busA = 32'h01010101; busB = 32'h0000000F; 
		#d;
		#(3*d);
		$stop; 
		$finish;
	end

endmodule

Lab3/sourceCode/tests/shiftlltest.vcd
$date
	Tue May 05 17:49:25 2015
$end
$version
	Icarus Verilog
$end
$timescale
	1s
$end
$scope module shiftllTest $end
$scope module shiftll $end
$var wire 32 ! Level1 [31:0] $end
$var wire 32 " Level2 [31:0] $end
$var wire 32 # busA [31:0] $end
$var wire 32 $ busSLL [31:0] $end
$var wire 32 % sel [31:0] $end
$upscope $end
$upscope $end
$enddefinitions $end
#0
$dumpvars
b1 %
b10000000100000001000000010 $
b1000000010000000100000001 #
b1000000010000000100000001 "
b1000000010000000100000001 !
$end
#20
b100000001000000010000000100 !
b100000001000000010000000100 $
b10 %
#40
b1000000010000000100000001000 $
b11 %
#60
b10000000100000001000000010000 "
b10000000100000001000000010000 !
b10000000100000001000000010000 $
b100 %
#80
b100000001000000010000000100000 $
b101 %
#100
b1000000010000000100000001000000 !
b1000000010000000100000001000000 $
b110 %
#120
b10000000100000001000000010000000 $
b111 %
#140
b1111 %
