Lab2/sourceCode/Implementation Details/registerSingle.sv

module registerSingle (
	input clk,
	input rst,    // active low reset
	input writeEnable, // Read is high, write is low; Active low write enable
	input writeData,  // Asynchronous reset active low
	output readData
);
	wire qBar;
	wire ns;
	mux2_1 mux(ns, writeData, readData, writeEnable);
	DFlipFlop register (readData, qBar, ns, clk, rst);
endmodule

Lab2/sourceCode/mux2_1.sv
module mux2_1(out, i0, i1, sel);
		output out;
		input i0, i1, sel;
		
		wire out1, out2, NOTsel;
		not n(NOTsel, sel);
		
		and a1(out1, i1, sel);
		and a2(out2, i0, NOTsel);
		or o(out, out1, out2);
endmodule

module mux2_1_testbench();
		reg i0, i1, sel;
		wire out;
		
		mux2_1 dut (.out, .i0, .i1, .sel);
		
		initial begin
				sel = 0; i0 = 0; i1 = 0; #10;
				sel = 0; i0 = 0; i1 = 1; #10;
				sel = 0; i0 = 1; i1 = 0; #10;
				sel = 0; i0 = 1; i1 = 1; #10;
				sel = 1; i0 = 0; i1 = 0; #10;
				sel = 1; i0 = 0; i1 = 1; #10;
				sel = 1; i0 = 1; i1 = 0; #10;
				sel = 1; i0 = 1; i1 = 1; #10;
		end
endmodule

Lab2/sourceCode/mux4_1.sv

module mux4_1(out, i00, i01, i10, i11, sel0, sel1);
		output out;
		input i00, i01, i10, i11, sel0, sel1;
		
		wire v0, v1;
		
		mux2_1 m0(.out(v0), .i0(i00), .i1(i01), .sel(sel0));
		mux2_1 m1(.out(v1), .i0(i10), .i1(i11), .sel(sel1));
		mux2_1 m(.out(out), .i0(v0) , .i1(v1) , .sel(sel1));
endmodule 

// module mux4_1_testbench();
// 		reg i00, i01, i10, i11, sel0, sel1;
// 		wire out;
		
// 		mux4_1 dut (.out, .i00, .i01, .i10, .i11, .sel0, .sel1);
		
// 		integer counter;
// 		initial begin
// 				for (counter = 0; counter < 64; counter++) begin
// 						{sel1, sel0, i00, i01, i10, i11} = counter; #10;
// 				end
// 		end
// endmodule

Lab2/sourceCode/mux8_1.sv

module mux8_1(out, i000, i001, i010, i011, i100, i101, i110, i111, sel0, sel1, sel2);
		output out;
		input i000, i001, i010, i011, i100, i101, i110, i111;
		input sel0, sel1, sel2;
		
		wire v0, v1;
		
		mux4_1 m0(.out(v0), .i00(i000), .i01(i001), .i10(i010), .i11(i011), .sel0(sel0), .sel1(sel1));
		mux4_1 m1(.out(v1), .i00(i100), .i01(i101), .i10(i110), .i11(i111), .sel0(sel1), .sel1(sel2));
		mux2_1 m(.out(out), .i0(v0) , .i1(v1) , .sel(sel2));
endmodule

Lab2/sourceCode/mux32_1.sv
module mux32_1 (
	output out,
	input [31:0] in,
	input [4:0] sel
);
	wire v0, v1, v2, v3;
	mux8_1 m0(v0, in[0], in[1], in[2], in[3], in[4], in[5], in[6], in[7], sel[0], sel[1], sel[2]);
	mux8_1 m1(v1, in[8], in[9], in[10], in[11], in[12], in[13], in[14], in[15], sel[1], sel[2], sel[3]);
	mux8_1 m2(v2, in[16], in[17], in[18], in[19], in[20], in[21], in[22], in[23], sel[2], sel[3], sel[4]);
	mux8_1 m3(v3, in[24], in[25], in[26], in[27], in[28], in[29], in[30], in[31], sel[3], sel[4], sel[0]);
	mux4_1 m(.out(out), .i00(v0), .i01(v1), .i10(v2), .i11(v3), .sel0(sel[3]), .sel1(sel[4]));
endmodule

Lab2/sourceCode/mux32by32_32.sv
// It is a two dimensional multiplexer designed for multi words register file.
// @requires: a 32 by 32 stack input with each row storing one word;
// @returns:  find bits from each column using a 32 to 1 mux, and form a 32 bit output.
module mux32by32_32 (
	output [31:0] out,
	input [31:0] in [31:0],
	input [4:0] sel
);
	genvar i, j;

	generate
		for (j = 0; j < 32; j = j + 1) begin: muxLoop
			reg [31:0] bitCompare;
			for (i = 0; i < 32; i = i + 1) begin: formARow
				buf e1(bitCompare[i], in[i][j]);
			end
			mux32_1 mux (out[j], bitCompare, sel);
		end
	endgenerate
	
endmodule

Lab 1/sourceCode/DFlipFlop.v
module DFlipFlop(q, qBar, D, clk, rst);
	input D, clk, rst;
	output q, qBar;
	reg q;
	not n1 (qBar, q);
	
	always@ (negedge rst or posedge clk)
	begin
		if(!rst)
			q = 0;
		else
			q = D;
	end
endmodule

Lab2/sourceCode/register.sv
module register (
	input clk,    // Clock
	input rst,    // active low reset
	input writeEnable, // Write Enable
	input [31:0] writeData,  // Asynchronous reset active low
	output [31:0] readData
);
	wire [31:0] qBar;
	reg [31:0] out;
	genvar j;

	assign out = (writeEnable) ? writeData : readData;
		
	generate
		for (j = 0; j < 32; j++) begin: registerLoopj
			DFlipFlop registerj (readData[j], qBar[j], readData[j], clk, rst);
		end
	endgenerate
endmodule

Lab2/sourceCode/decoder5_32.sv
// It's a five to one of thirty-two decoder.
// @requires:	five bit of data address;
// @returns:	thirty two bit of an array of zero with only a single one.
module decoder5_32 (
	input [4:0] in,  
	output [31:0] out
);
	wire [4:0] no;
	genvar i, j;
	generate		
		for (i = 0; i < 5; i = i + 1) begin: notLineLoop
			not n1(no[i], in[i]);
		end
	endgenerate
	and n00000(out[0], in[0], in[1], in[2], in[3], in[4]);
	and n10000(out[1], no[0], in[1], in[2], in[3], in[4]);
	and n01000(out[2], in[0], no[1], in[2], in[3], in[4]);
	and n11000(out[3], no[0], no[1], in[2], in[3], in[4]);
	and n00100(out[4], in[0], in[1], no[2], in[3], in[4]);
	and n10100(out[5], no[0], in[1], no[2], in[3], in[4]);
	and n01100(out[6], in[0], no[1], no[2], in[3], in[4]);
	and n11100(out[7], no[0], no[1], no[2], in[3], in[4]);
	and n00010(out[8], in[0], in[1], in[2], no[3], in[4]);
	and n10010(out[9], no[0], in[1], in[2], no[3], in[4]);
	and n01010(out[10], in[0], no[1], in[2], no[3], in[4]);	
	and n11010(out[11], no[0], no[1], in[2], no[3], in[4]);	
	and n00110(out[12], in[0], in[1], no[2], no[3], in[4]);
	and n10110(out[13], no[0], in[1], no[2], no[3], in[4]);	
	and n01110(out[14], in[0], no[1], no[2], no[3], in[4]);	
	and n11110(out[15], no[0], no[1], no[2], no[3], in[4]);

	and n00001(out[16], in[0], in[1], in[2], in[3], no[4]);
	and n10001(out[17], no[0], in[1], in[2], in[3], no[4]);
	and n01001(out[18], in[0], no[1], in[2], in[3], no[4]);
	and n11001(out[19], no[0], no[1], in[2], in[3], no[4]);
	and n00101(out[20], in[0], in[1], no[2], in[3], no[4]);
	and n10101(out[21], no[0], in[1], no[2], in[3], no[4]);
	and n01101(out[22], in[0], no[1], no[2], in[3], no[4]);
	and n11101(out[23], no[0], no[1], no[2], in[3], no[4]);
	and n00011(out[24], in[0], in[1], in[2], no[3], no[4]);
	and n10011(out[25], no[0], in[1], in[2], no[3], no[4]);
	and n01011(out[26], in[0], no[1], in[2], no[3], no[4]);	
	and n11011(out[27], no[0], no[1], in[2], no[3], no[4]);	
	and n00111(out[28], in[0], in[1], no[2], no[3], no[4]);
	and n10111(out[29], no[0], in[1], no[2], no[3], no[4]);	
	and n01111(out[30], in[0], no[1], no[2], no[3], no[4]);	
	and n11111(out[31], no[0], no[1], no[2], no[3], no[4]);	
endmodule

Lab2/sourceCode/registerFile.sv
// UWEE, Beck Pang, Raymond Mui, Andrew J. Townsend
// EE 471 Lab 2, Apr.20, 2015
// This module is a piece of a synchronous memory system that store the most accessed data
// called register file, with 32 registers of 32 bit wide.
// The first register is set as ground reference and always output
// It takes clock, address and signals from the system bus, 
// have both read or write function, read data from or write data to registers.
// Read Operation:
//	@requires:  a clock signal, a low signal for write enable,
// 			two read address width of 5 bits;
//	@returns:	a data of 32 bits specified by the address;
// Write Operation:
//  @requires:	a clock signal, a high signal for write enable,
// 			a write address with width of 5 bits, and an data with width of 32 bits;
// 	@modifies:	the data of the address passed in

// `include "decoder5_32.sv"
// `include "register.sv"
// `include "mux32by32_32.sv"
module registerFile (
	input clk, 
	input [4:0] regReadSel0, regReadSel1, regWriteSel,
	input writeEnable, // Write Enable
	input [31:0] writeData, 
	output [31:0] regReadData0, regReadData1
);
	wire regReadIndex;

	// The address to write
	wire [31:0] writeEnableDecoded;
	reg  [31:0] wrote;
	reg [31:0] RF [31:0];
	reg rst = 1'b0;

	// Step1: Decode the write address with writeEnable
	decoder5_32 writeDecode(regWriteSel, writeEnableDecoded);

	genvar i;
	generate
		for (i = 0; i < 32; i = i + 1) begin: wroteEnableLoop
			and wroteEnableAnd(wrote[i], writeEnable, writeEnableDecoded[i]);
		end
	endgenerate

	// Step2: form the RF with each row storing one word of 32 bit
	// Register 0 always output 0
	register reg0(clk, rst, wrote[0], 32'bx, RF[0]);
	
	genvar j;

	generate
		for (j = 1; j < 32; j = j + 1) begin: registerLoopj
			register regj (clk, ~rst, wrote[j], writeData, RF[j]);
		end
	endgenerate

	// Step3: using a mux to extrace a 32 bit word from the read address
	mux32by32_32 regMux0(regReadData0, RF, regReadSel0);
	mux32by32_32 regMux1(regReadData1, RF, regReadSel1);

endmodule

Lab2/sourceCode/registerFileTest.sv
// Beck Pang
// University of Washington, Seattle
// Apr. 6th, 2015
// EE 471, Lab 1

`include "registerFile.sv"
`include "decoder5_32.sv"
`include "register.sv"
`include "registerSingle.sv"
`include "mux32_1.sv"
`include "mux8_1.sv"
`include "mux4_1.sv"
`include "mux2_1.sv"
`include "DFlipFlop.sv"
// test bench running on gtkwave
module registerFile_testBench();

	// connext the two modules
	wire clk;
	wire [4:0] regReadSel0, regReadSel1, regWriteSel;
	wire writeEnable; // Write Enable
	wire [31:0] writeData; 
	wire [31:0] regReadData0, regReadData1;

	// declare an instance of the AND module
	registerFile registerList (clk, regReadSel0, regReadSel1, regWriteSel,
	 writeEnable, writeData, regReadData0, regReadData1);

	// Running the GUI part of simulation
	registerFile_Tester aTester (clk, regReadSel0, regReadSel1, regWriteSel,
	 writeEnable, writeData, regReadData0, regReadData1);

	// file for gtkwave

	initial
	begin
		$dumpfile("registerFile.vcd");
		$dumpvars(1, registerList);
	end

endmodule

module registerFile_Tester (
	output reg clk, 
	output reg [4:0] regReadSel0, regReadSel1, regWriteSel,
	output reg writeEnable, // Write Enable
	output [31:0] writeData, 
	input [31:0] regReadData0, regReadData1
);
	reg [31:0] newWriteData;
	parameter stimDelay = 20;

	// generate a clock
	always #(stimDelay/2) clk = ~clk;

	assign writeData = writeEnable ? 16'bZ : newWriteData;

	initial // Response
	begin
		$display("\t\t clk \t writeEnable \t regReadSel0 \t regReadSel1 \t regWriteSel \t writeData \t regReadData0 \t regReadData1 \t  Time ");
		$monitor("\t %b ", writeData, $time);
		$monitor("\t %b \t %b ", clk, writeEnable, $time);
		$monitor("\t %b \t %b ", regReadData0, regReadData1, $time);
		$monitor("\t %b \t %b \t %b",regReadSel0, regReadSel1, regWriteSel , $time);
		clk = 'b0;
	end

	reg [4:0] i, j;
	always @(posedge clk) // Stimulus
	begin
					writeEnable = 1'b1;
		// A full cycle to write
		writeEnable = #stimDelay 1'b1; 
		writeEnable = #stimDelay 1'b0;
		regReadSel0 = 5'b00000;
		regReadSel1 = 5'b00011; 
		for (i = 0; i < 16; i = i + 1) begin
			regWriteSel = 5'b00000 + i; 
			newWriteData  = 32'hFFFF000F - i;
			#stimDelay;
		end
		writeEnable = 5'b1; #(20*stimDelay); 
		writeEnable = 5'b0; #stimDelay;

		for (j = 0; j < 16; j = j + 1) begin
			regWriteSel = 5'b10000 + j; 
			newWriteData   = 32'h0000FFF0 + j; 
			#stimDelay;
		end
		writeEnable = 5'b1; #stimDelay; 
		writeEnable = 5'b1; #(20*stimDelay); 

		$stop;
		$finish;
	end

endmodule

Lab2/sourceCode/registerFile.vcd
$date
	Tue Apr 21 21:48:10 2015
$end
$version
	Icarus Verilog
$end
$timescale
	1s
$end
$scope module registerFile_testBench $end
$scope module registerList $end
$var wire 1 ! clk $end
$var wire 32 " regReadData0 [31:0] $end
$var wire 32 # regReadData1 [31:0] $end
$var wire 5 $ regReadSel0 [4:0] $end
$var wire 5 % regReadSel1 [4:0] $end
$var wire 5 & regWriteSel [4:0] $end
$var wire 32 ' writeData [31:0] $end
$var wire 1 ( writeEnable $end
$var wire 32 ) writeEnableDecoded [31:0] $end
$var wire 32 * wrote [31:0] $end
$var reg 1 + rst $end
$upscope $end
$upscope $end
$enddefinitions $end
#0
$dumpvars
0+
bx *
bx )
x(
bx '
bx &
bx %
bx $
bx #
bx "
0!
$end
#10
b0zzzzzzzzzzzzzzzz '
b11111111111111111111111111111111 *
1(
1!
#20
0!
#30
1!
#40
0!
#50
b0 "
b11111111111111111111111111111110 )
b11111111111111110000000000001111 '
b11111111111111111111111111111110 *
1!
b0 &
b11 %
b0 $
0(
#60
0!
#70
b11111111111111111111111111111101 *
b11111111111111111111111111111101 )
b11111111111111110000000000001110 '
1!
b1 &
#80
0!
#90
b11111111111111111111111111111011 *
b11111111111111111111111111111011 )
b11111111111111110000000000001101 '
1!
b10 &
#100
0!
#110
b11111111111111111111111111110111 *
b11111111111111111111111111110111 )
b11111111111111110000000000001100 '
1!
b11 &
#120
0!
#130
b11111111111111110000000000001100 #
b11111111111111111111111111101111 *
b11111111111111111111111111101111 )
b11111111111111110000000000001011 '
1!
b100 &
#140
0!
#150
b11111111111111111111111111011111 *
b11111111111111111111111111011111 )
b11111111111111110000000000001010 '
1!
b101 &
#160
0!
#170
b11111111111111111111111110111111 *
b11111111111111111111111110111111 )
b11111111111111110000000000001001 '
1!
b110 &
#180
0!
#190
b11111111111111111111111101111111 *
b11111111111111111111111101111111 )
b11111111111111110000000000001000 '
1!
b111 &
#200
0!
#210
b11111111111111111111111011111111 *
b11111111111111111111111011111111 )
b11111111111111110000000000000111 '
1!
b1000 &
#220
0!
#230
b11111111111111111111110111111111 *
b11111111111111111111110111111111 )
b11111111111111110000000000000110 '
1!
b1001 &
#240
0!
#250
b11111111111111111111101111111111 *
b11111111111111111111101111111111 )
b11111111111111110000000000000101 '
1!
b1010 &
#260
0!
#270
b11111111111111111111011111111111 *
b11111111111111111111011111111111 )
b11111111111111110000000000000100 '
1!
b1011 &
#280
0!
#290
b11111111111111111110111111111111 *
b11111111111111111110111111111111 )
b11111111111111110000000000000011 '
1!
b1100 &
#300
0!
#310
b11111111111111111101111111111111 *
b11111111111111111101111111111111 )
b11111111111111110000000000000010 '
1!
b1101 &
#320
0!
#330
b11111111111111111011111111111111 *
b11111111111111111011111111111111 )
b11111111111111110000000000000001 '
1!
b1110 &
#340
0!
#350
b11111111111111110111111111111111 *
b11111111111111110111111111111111 )
b11111111111111110000000000000000 '
1!
b1111 &
#360
0!
#370
b0zzzzzzzzzzzzzzzz '
b11111111111111111111111111111111 *
1!
1(
#380
0!
#390
1!
#400
0!
#410
1!
#420
0!
#430
1!
#440
0!
#450
1!
#460
0!
#470
1!
#480
0!
#490
1!
#500
0!
#510
1!
#520
0!
#530
1!
#540
0!
#550
1!
#560
0!
#570
1!
#580
0!
#590
1!
#600
0!
#610
1!
#620
0!
#630
1!
#640
0!
#650
1!
#660
0!
#670
1!
#680
0!
#690
1!
#700
0!
#710
1!
#720
0!
#730
1!
#740
0!
#750
1!
#760
0!
#770
b11111111111111110000000000000000 '
b11111111111111110111111111111111 *
1!
0(
#780
0!
#790
b11111111111111101111111111111111 *
b11111111111111101111111111111111 )
b1111111111110000 '
1!
b10000 &
#800
0!
#810
b11111111111111011111111111111111 *
b11111111111111011111111111111111 )
b1111111111110001 '
1!
b10001 &
#820
0!
#830
b11111111111110111111111111111111 *
b11111111111110111111111111111111 )
b1111111111110010 '
1!
b10010 &
#840
0!
#850
b11111111111101111111111111111111 *
b11111111111101111111111111111111 )
b1111111111110011 '
1!
b10011 &
#860
0!
#870
b11111111111011111111111111111111 *
b11111111111011111111111111111111 )
b1111111111110100 '
1!
b10100 &
#880
0!
#890
b11111111110111111111111111111111 *
b11111111110111111111111111111111 )
b1111111111110101 '
1!
b10101 &
#900
0!
#910
b11111111101111111111111111111111 *
b11111111101111111111111111111111 )
b1111111111110110 '
1!
b10110 &
#920
0!
#930
b11111111011111111111111111111111 *
b11111111011111111111111111111111 )
b1111111111110111 '
1!
b10111 &
#940
0!
#950
b11111110111111111111111111111111 *
b11111110111111111111111111111111 )
b1111111111111000 '
1!
b11000 &
#960
0!
#970
b11111101111111111111111111111111 *
b11111101111111111111111111111111 )
b1111111111111001 '
1!
b11001 &
#980
0!
#990
b11111011111111111111111111111111 *
b11111011111111111111111111111111 )
b1111111111111010 '
1!
b11010 &
#1000
0!
#1010
b11110111111111111111111111111111 *
b11110111111111111111111111111111 )
b1111111111111011 '
1!
b11011 &
#1020
0!
#1030
b11101111111111111111111111111111 *
b11101111111111111111111111111111 )
b1111111111111100 '
1!
b11100 &
#1040
0!
#1050
b11011111111111111111111111111111 *
b11011111111111111111111111111111 )
b1111111111111101 '
1!
b11101 &
#1060
0!
#1070
b10111111111111111111111111111111 *
b10111111111111111111111111111111 )
b1111111111111110 '
1!
b11110 &
#1080
0!
#1090
b1111111111111111111111111111111 *
b1111111111111111111111111111111 )
b1111111111111111 '
1!
b11111 &
#1100
0!
#1110
b0zzzzzzzzzzzzzzzz '
b11111111111111111111111111111111 *
1!
1(
