Lab2/sourceCode/SRAM2Kby16.v
// AJ, Beck, and Ray
// SRAM module
// 4/21/15

module SRAM2Kby16(clk, adx, WrEn, data);
	input clk, WrEn;
	input [10:0] adx;
	inout [15:0] data;

	reg [15:0]SRAM[2047:0]; // memory regs
	
	assign data = (WrEn) ? SRAM[adx] : 16'bZ; // control the tri-state 
	
	always @(posedge clk) begin
		if(~WrEn) 
				SRAM[adx] = data; // assign the SRAM index to data
	end
	
	initial begin
		SRAM[10] = 47;
	end
endmodule

Lab2/sourceCode/SRAMtest.sv
// AJ, Beck, and Ray
// SRAM testbench
// 4/21/15

`include "SRAM2Kby16.v"
module SRAMtest();

	// localize variables
	wire clk, WrEn;
	wire [10:0] adx;
	wire [15:0] data;

	// declare an instance of the module
	SRAM2Kby16 SRAM (clk, adx, WrEn, data);

	// Running the GUI part of simulation
	SRAMtester tester (clk, adx, WrEn, data);

	// file for gtkwave

	initial
	begin
		$dumpfile("SRAMtest.vcd");
		$dumpvars(1, SRAM);
	end

endmodule

module SRAMtester (clk, adx, WrEn, data);
	input clk, WrEn;
	input [11:0] adx;
	inout [15:0] data;
	reg out;
	parameter d = 20;

	// generate a clock
	always #(d/2) clk = ~clk;
	
	assign data = WrEn ? 16'bZ : out;

	initial // Response
	begin
		$display("\t\t clk \t WrEn \t adx \t data  Time ");
		$monitor("\t %b \t %b \t %b \t %b ", clk, WrEn, adx, data, $time);
	end

	always @(posedge clk) // Stimulus
	begin
		WrEn = 1; adx = 0; out = 1;
		#d
		WrEn = 0;
		for(int i = 0; i < 128; i++) begin
			adx = i;
			out = 127 - i;
			#d
		end
		WrEn = 1;
		for(int i = 0; i < 128; i++) begin
			adx = i;
			#d
		end
		#(2*d); // end bias
		$stop; 
		$finish;
	end

endmodule

Lab2/sourceCode/SRAMtest.vcd
$date
	Tue Apr 21 18:59:29 2015
$end
$version
	Icarus Verilog
$end
$timescale
	1s
$end
$scope module SRAMtest $end
$scope module SRAM $end
$var wire 1 ! WrEn $end
$var wire 11 " adx [10:0] $end
$var wire 1 # clk $end
$var wire 16 $ data [15:0] $end
$upscope $end
$upscope $end
$enddefinitions $end
#0
$dumpvars
bx $
x#
b0 "
1!
$end
#20
1#
#30
0#
#40
1#
#50
0#
#60
1#
#70
0#
#80
1#
#90
0#
#100
1#
#110
0#
#120
1#
#130
0#
#140
1#
#150
0#
#160
1#
#170
0#
#180
1#
#190
0#
#200
b1111111 $
1#
0!
#210
0#
#220
b1111110 $
1#
b1 "
#230
0#
#240
b1111101 $
1#
b10 "
#250
0#
#260
b1111100 $
1#
b11 "
#270
0#
#280
b1111011 $
1#
b100 "
#290
0#
#300
b1111010 $
1#
b101 "
#310
0#
#320
b1111001 $
1#
b110 "
#330
0#
#340
b1111000 $
1#
b111 "
#350
0#
#360
b1110111 $
1#
b1000 "
#370
0#
#380
b1110110 $
1#
b1001 "
#390
0#
#400
b1110101 $
1#
b1010 "
#410
0#
#420
b1110100 $
1#
b1011 "
#430
0#
#440
b1110011 $
1#
b1100 "
#450
0#
#460
b1110010 $
1#
b1101 "
#470
0#
#480
b1110001 $
1#
b1110 "
#490
0#
#500
b1110000 $
1#
b1111 "
#510
0#
#520
b1101111 $
1#
b10000 "
#530
0#
#540
b1101110 $
1#
b10001 "
#550
0#
#560
b1101101 $
1#
b10010 "
#570
0#
#580
b1101100 $
1#
b10011 "
#590
0#
#600
b1101011 $
1#
b10100 "
#610
0#
#620
b1101010 $
1#
b10101 "
#630
0#
#640
b1101001 $
1#
b10110 "
#650
0#
#660
b1101000 $
1#
b10111 "
#670
0#
#680
b1100111 $
1#
b11000 "
#690
0#
#700
b1100110 $
1#
b11001 "
#710
0#
#720
b1100101 $
1#
b11010 "
#730
0#
#740
b1100100 $
1#
b11011 "
#750
0#
#760
b1100011 $
1#
b11100 "
#770
0#
#780
b1100010 $
1#
b11101 "
#790
0#
#800
b1100001 $
1#
b11110 "
#810
0#
#820
b1100000 $
1#
b11111 "
#830
0#
#840
b1011111 $
1#
b100000 "
#850
0#
#860
b1011110 $
1#
b100001 "
#870
0#
#880
b1011101 $
1#
b100010 "
#890
0#
#900
b1011100 $
1#
b100011 "
#910
0#
#920
b1011011 $
1#
b100100 "
#930
0#
#940
b1011010 $
1#
b100101 "
#950
0#
#960
b1011001 $
1#
b100110 "
#970
0#
#980
b1011000 $
1#
b100111 "
#990
0#
#1000
b1010111 $
1#
b101000 "
#1010
0#
#1020
b1010110 $
1#
b101001 "
#1030
0#
#1040
b1010101 $
1#
b101010 "
#1050
0#
#1060
b1010100 $
1#
b101011 "
#1070
0#
#1080
b1010011 $
1#
b101100 "
#1090
0#
#1100
b1010010 $
1#
b101101 "
#1110
0#
#1120
b1010001 $
1#
b101110 "
#1130
0#
#1140
b1010000 $
1#
b101111 "
#1150
0#
#1160
b1001111 $
1#
b110000 "
#1170
0#
#1180
b1001110 $
1#
b110001 "
#1190
0#
#1200
b1001101 $
1#
b110010 "
#1210
0#
#1220
b1001100 $
1#
b110011 "
#1230
0#
#1240
b1001011 $
1#
b110100 "
#1250
0#
#1260
b1001010 $
1#
b110101 "
#1270
0#
#1280
b1001001 $
1#
b110110 "
#1290
0#
#1300
b1001000 $
1#
b110111 "
#1310
0#
#1320
b1000111 $
1#
b111000 "
#1330
0#
#1340
b1000110 $
1#
b111001 "
#1350
0#
#1360
b1000101 $
1#
b111010 "
#1370
0#
#1380
b1000100 $
1#
b111011 "
#1390
0#
#1400
b1000011 $
1#
b111100 "
#1410
0#
#1420
b1000010 $
1#
b111101 "
#1430
0#
#1440
b1000001 $
1#
b111110 "
#1450
0#
#1460
b1000000 $
1#
b111111 "
#1470
0#
#1480
b111111 $
1#
b1000000 "
#1490
0#
#1500
b111110 $
1#
b1000001 "
#1510
0#
#1520
b111101 $
1#
b1000010 "
#1530
0#
#1540
b111100 $
1#
b1000011 "
#1550
0#
#1560
b111011 $
1#
b1000100 "
#1570
0#
#1580
b111010 $
1#
b1000101 "
#1590
0#
#1600
b111001 $
1#
b1000110 "
#1610
0#
#1620
b111000 $
1#
b1000111 "
#1630
0#
#1640
b110111 $
1#
b1001000 "
#1650
0#
#1660
b110110 $
1#
b1001001 "
#1670
0#
#1680
b110101 $
1#
b1001010 "
#1690
0#
#1700
b110100 $
1#
b1001011 "
#1710
0#
#1720
b110011 $
1#
b1001100 "
#1730
0#
#1740
b110010 $
1#
b1001101 "
#1750
0#
#1760
b110001 $
1#
b1001110 "
#1770
0#
#1780
b110000 $
1#
b1001111 "
#1790
0#
#1800
b101111 $
1#
b1010000 "
#1810
0#
#1820
b101110 $
1#
b1010001 "
#1830
0#
#1840
b101101 $
1#
b1010010 "
#1850
0#
#1860
b101100 $
1#
b1010011 "
#1870
0#
#1880
b101011 $
1#
b1010100 "
#1890
0#
#1900
b101010 $
1#
b1010101 "
#1910
0#
#1920
b101001 $
1#
b1010110 "
#1930
0#
#1940
b101000 $
1#
b1010111 "
#1950
0#
#1960
b100111 $
1#
b1011000 "
#1970
0#
#1980
b100110 $
1#
b1011001 "
#1990
0#
#2000
b100101 $
1#
b1011010 "
#2010
0#
#2020
b100100 $
1#
b1011011 "
#2030
0#
#2040
b100011 $
1#
b1011100 "
#2050
0#
#2060
b100010 $
1#
b1011101 "
#2070
0#
#2080
b100001 $
1#
b1011110 "
#2090
0#
#2100
b100000 $
1#
b1011111 "
#2110
0#
#2120
b11111 $
1#
b1100000 "
#2130
0#
#2140
b11110 $
1#
b1100001 "
#2150
0#
#2160
b11101 $
1#
b1100010 "
#2170
0#
#2180
b11100 $
1#
b1100011 "
#2190
0#
#2200
b11011 $
1#
b1100100 "
#2210
0#
#2220
b11010 $
1#
b1100101 "
#2230
0#
#2240
b11001 $
1#
b1100110 "
#2250
0#
#2260
b11000 $
1#
b1100111 "
#2270
0#
#2280
b10111 $
1#
b1101000 "
#2290
0#
#2300
b10110 $
1#
b1101001 "
#2310
0#
#2320
b10101 $
1#
b1101010 "
#2330
0#
#2340
b10100 $
1#
b1101011 "
#2350
0#
#2360
b10011 $
1#
b1101100 "
#2370
0#
#2380
b10010 $
1#
b1101101 "
#2390
0#
#2400
b10001 $
1#
b1101110 "
#2410
0#
#2420
b10000 $
1#
b1101111 "
#2430
0#
#2440
b1111 $
1#
b1110000 "
#2450
0#
#2460
b1110 $
1#
b1110001 "
#2470
0#
#2480
b1101 $
1#
b1110010 "
#2490
0#
#2500
b1100 $
1#
b1110011 "
#2510
0#
#2520
b1011 $
1#
b1110100 "
#2530
0#
#2540
b1010 $
1#
b1110101 "
#2550
0#
#2560
b1001 $
1#
b1110110 "
#2570
0#
#2580
b1000 $
1#
b1110111 "
#2590
0#
#2600
b111 $
1#
b1111000 "
#2610
0#
#2620
b110 $
1#
b1111001 "
#2630
0#
#2640
b101 $
1#
b1111010 "
#2650
0#
#2660
b100 $
1#
b1111011 "
#2670
0#
#2680
b11 $
1#
b1111100 "
#2690
0#
#2700
b10 $
1#
b1111101 "
#2710
0#
#2720
b1 $
1#
b1111110 "
#2730
0#
#2740
b0 $
1#
b1111111 "
#2750
0#
#2760
b1111111 $
1#
b0 "
1!
#2770
0#
#2780
b1111110 $
1#
b1 "
#2790
0#
#2800
b1111101 $
1#
b10 "
#2810
0#
#2820
b1111100 $
1#
b11 "
#2830
0#
#2840
b1111011 $
1#
b100 "
#2850
0#
#2860
b1111010 $
1#
b101 "
#2870
0#
#2880
b1111001 $
1#
b110 "
#2890
0#
#2900
b1111000 $
1#
b111 "
#2910
0#
#2920
b1110111 $
1#
b1000 "
#2930
0#
#2940
b1110110 $
1#
b1001 "
#2950
0#
#2960
b1110101 $
1#
b1010 "
#2970
0#
#2980
b1110100 $
1#
b1011 "
#2990
0#
#3000
b1110011 $
1#
b1100 "
#3010
0#
#3020
b1110010 $
1#
b1101 "
#3030
0#
#3040
b1110001 $
1#
b1110 "
#3050
0#
#3060
b1110000 $
1#
b1111 "
#3070
0#
#3080
b1101111 $
1#
b10000 "
#3090
0#
#3100
b1101110 $
1#
b10001 "
#3110
0#
#3120
b1101101 $
1#
b10010 "
#3130
0#
#3140
b1101100 $
1#
b10011 "
#3150
0#
#3160
b1101011 $
1#
b10100 "
#3170
0#
#3180
b1101010 $
1#
b10101 "
#3190
0#
#3200
b1101001 $
1#
b10110 "
#3210
0#
#3220
b1101000 $
1#
b10111 "
#3230
0#
#3240
b1100111 $
1#
b11000 "
#3250
0#
#3260
b1100110 $
1#
b11001 "
#3270
0#
#3280
b1100101 $
1#
b11010 "
#3290
0#
#3300
b1100100 $
1#
b11011 "
#3310
0#
#3320
b1100011 $
1#
b11100 "
#3330
0#
#3340
b1100010 $
1#
b11101 "
#3350
0#
#3360
b1100001 $
1#
b11110 "
#3370
0#
#3380
b1100000 $
1#
b11111 "
#3390
0#
#3400
b1011111 $
1#
b100000 "
#3410
0#
#3420
b1011110 $
1#
b100001 "
#3430
0#
#3440
b1011101 $
1#
b100010 "
#3450
0#
#3460
b1011100 $
1#
b100011 "
#3470
0#
#3480
b1011011 $
1#
b100100 "
#3490
0#
#3500
b1011010 $
1#
b100101 "
#3510
0#
#3520
b1011001 $
1#
b100110 "
#3530
0#
#3540
b1011000 $
1#
b100111 "
#3550
0#
#3560
b1010111 $
1#
b101000 "
#3570
0#
#3580
b1010110 $
1#
b101001 "
#3590
0#
#3600
b1010101 $
1#
b101010 "
#3610
0#
#3620
b1010100 $
1#
b101011 "
#3630
0#
#3640
b1010011 $
1#
b101100 "
#3650
0#
#3660
b1010010 $
1#
b101101 "
#3670
0#
#3680
b1010001 $
1#
b101110 "
#3690
0#
#3700
b1010000 $
1#
b101111 "
#3710
0#
#3720
b1001111 $
1#
b110000 "
#3730
0#
#3740
b1001110 $
1#
b110001 "
#3750
0#
#3760
b1001101 $
1#
b110010 "
#3770
0#
#3780
b1001100 $
1#
b110011 "
#3790
0#
#3800
b1001011 $
1#
b110100 "
#3810
0#
#3820
b1001010 $
1#
b110101 "
#3830
0#
#3840
b1001001 $
1#
b110110 "
#3850
0#
#3860
b1001000 $
1#
b110111 "
#3870
0#
#3880
b1000111 $
1#
b111000 "
#3890
0#
#3900
b1000110 $
1#
b111001 "
#3910
0#
#3920
b1000101 $
1#
b111010 "
#3930
0#
#3940
b1000100 $
1#
b111011 "
#3950
0#
#3960
b1000011 $
1#
b111100 "
#3970
0#
#3980
b1000010 $
1#
b111101 "
#3990
0#
#4000
b1000001 $
1#
b111110 "
#4010
0#
#4020
b1000000 $
1#
b111111 "
#4030
0#
#4040
b111111 $
1#
b1000000 "
#4050
0#
#4060
b111110 $
1#
b1000001 "
#4070
0#
#4080
b111101 $
1#
b1000010 "
#4090
0#
#4100
b111100 $
1#
b1000011 "
#4110
0#
#4120
b111011 $
1#
b1000100 "
#4130
0#
#4140
b111010 $
1#
b1000101 "
#4150
0#
#4160
b111001 $
1#
b1000110 "
#4170
0#
#4180
b111000 $
1#
b1000111 "
#4190
0#
#4200
b110111 $
1#
b1001000 "
#4210
0#
#4220
b110110 $
1#
b1001001 "
#4230
0#
#4240
b110101 $
1#
b1001010 "
#4250
0#
#4260
b110100 $
1#
b1001011 "
#4270
0#
#4280
b110011 $
1#
b1001100 "
#4290
0#
#4300
b110010 $
1#
b1001101 "
#4310
0#
#4320
b110001 $
1#
b1001110 "
#4330
0#
#4340
b110000 $
1#
b1001111 "
#4350
0#
#4360
b101111 $
1#
b1010000 "
#4370
0#
#4380
b101110 $
1#
b1010001 "
#4390
0#
#4400
b101101 $
1#
b1010010 "
#4410
0#
#4420
b101100 $
1#
b1010011 "
#4430
0#
#4440
b101011 $
1#
b1010100 "
#4450
0#
#4460
b101010 $
1#
b1010101 "
#4470
0#
#4480
b101001 $
1#
b1010110 "
#4490
0#
#4500
b101000 $
1#
b1010111 "
#4510
0#
#4520
b100111 $
1#
b1011000 "
#4530
0#
#4540
b100110 $
1#
b1011001 "
#4550
0#
#4560
b100101 $
1#
b1011010 "
#4570
0#
#4580
b100100 $
1#
b1011011 "
#4590
0#
#4600
b100011 $
1#
b1011100 "
#4610
0#
#4620
b100010 $
1#
b1011101 "
#4630
0#
#4640
b100001 $
1#
b1011110 "
#4650
0#
#4660
b100000 $
1#
b1011111 "
#4670
0#
#4680
b11111 $
1#
b1100000 "
#4690
0#
#4700
b11110 $
1#
b1100001 "
#4710
0#
#4720
b11101 $
1#
b1100010 "
#4730
0#
#4740
b11100 $
1#
b1100011 "
#4750
0#
#4760
b11011 $
1#
b1100100 "
#4770
0#
#4780
b11010 $
1#
b1100101 "
#4790
0#
#4800
b11001 $
1#
b1100110 "
#4810
0#
#4820
b11000 $
1#
b1100111 "
#4830
0#
#4840
b10111 $
1#
b1101000 "
#4850
0#
#4860
b10110 $
1#
b1101001 "
#4870
0#
#4880
b10101 $
1#
b1101010 "
#4890
0#
#4900
b10100 $
1#
b1101011 "
#4910
0#
#4920
b10011 $
1#
b1101100 "
#4930
0#
#4940
b10010 $
1#
b1101101 "
#4950
0#
#4960
b10001 $
1#
b1101110 "
#4970
0#
#4980
b10000 $
1#
b1101111 "
#4990
0#
#5000
b1111 $
1#
b1110000 "
#5010
0#
#5020
b1110 $
1#
b1110001 "
#5030
0#
#5040
b1101 $
1#
b1110010 "
#5050
0#
#5060
b1100 $
1#
b1110011 "
#5070
0#
#5080
b1011 $
1#
b1110100 "
#5090
0#
#5100
b1010 $
1#
b1110101 "
#5110
0#
#5120
b1001 $
1#
b1110110 "
#5130
0#
#5140
b1000 $
1#
b1110111 "
#5150
0#
#5160
b111 $
1#
b1111000 "
#5170
0#
#5180
b110 $
1#
b1111001 "
#5190
0#
#5200
b101 $
1#
b1111010 "
#5210
0#
#5220
b100 $
1#
b1111011 "
#5230
0#
#5240
b11 $
1#
b1111100 "
#5250
0#
#5260
b10 $
1#
b1111101 "
#5270
0#
#5280
b1 $
1#
b1111110 "
#5290
0#
#5300
b0 $
1#
b1111111 "
