Lab3/sourceCode/flag.v
module flag (
	input [31:0] busOut, busA, busB, 
	input carryOut, 
	output z, o, c, n
);
	wire tempZ[7:0];
	// NOR gate will act 1 when all inputs are 0
	// assign z = ~|busOut[31:0];
	genvar i;
	generate
		for (i = 0; i < 8; i = i+1) begin: zeroLoop
			nor zero0(tempZ[i], busOut[0 + 4 * i], busOut[1 + 4 * i],busOut[2 + 4 * i],busOut[3 + 4 * i]);
		end
	endgenerate

	and zero8(z, tempZ[0], tempZ[1], tempZ[2], tempZ[3], tempZ[4], tempZ[5], tempZ[6], tempZ[7]);

	wire s1, s2;
	xnor part1(s1, busA[31], busB[31]);
	xor  part2(s2, busA[31], busOut[31]);
	and overflow(o, s1, s2);
	buf e1(c, carryOut);
	buf e2(n, busOut[31]);

endmodule

Lab3/sourceCode/lookAhead4b.v
module lookAhead4b(carryIn,g,p,GG,PG,c);
	input carryIn;
	input [3:0] g;
	input [3:0] p;
	output GG,PG;
	output [4:1] c;
	
	wire [3:0] temp;
	//assign c[1] = carryIn * p[0] + g[0];
	and a0(temp[0], carryIn, p[0]);
	or or0(c[1], g[0], temp[0]);
	//assign c[2] = c[1] * p[1] + g[1];
	and a1(temp[1], c[1], p[1]);
	or or1(c[2], g[1], temp[1]);
	//assign c[3] = c[2] * p[2] + g[2];
	and a2(temp[2], c[2], p[2]);
	or or2(c[3], g[2], temp[2]);
	//assign c[4] = c[3] * p[3] + g[3];
	and a3(temp[3], c[3], p[3]);
	or or3(c[4], g[3], temp[3]);
	
	// assign GG = g[3] | (p[3] & g[2]) | (p[3] & p[2] & g[1]) | (p[3] & p[2] & p[1] & g[0]);
	wire [2:0] PP;
	and a01(PP[0], g[0], p[1], p[2], p[3]);
	and a02(PP[1], g[1], p[2], p[3]);
	and a03(PP[2], g[2], p[3]);
	or or4(GG, g[3], PP[2], PP[1], PP[0]);
	
	// assign PG = p[3] * p[2] * p[1] * p[0] ;
	and a11(PG, p[3], p[2], p[1], p[0]);

endmodule

Lab3/sourceCode/fullAdder1b.v
module fullAdder1b(x,y,carryIn,G,P, S);
	input x,y,carryIn;
	output P, G, S;
	
	xor p(P, x, y);
	//assign P = x^y; // x XOR y
	and g(G, x, y);
	//assign G = x*y; // x AND y
	xor s(S, x, y, carryIn);
endmodule

Lab3/sourceCode/adder4b.v
module adder4b(carryIn,X,Y,S,G,P,carryOut);
	input carryIn;
	input [4:0] X;
	input [4:0] Y;
	output [4:0] S;
	wire [4:0] g;
	wire [4:0] p;
	output G;
	output P;
	output [4:0] carryOut;
	wire genCarry
	fullAdder1b a0(X[0],Y[0],carryIn,g[0],p[0]);
	fullAdder1b a1(X[1],Y[1],genCarry,g[1],p[1]);
	fullAdder1b a2(X[2],Y[2],genCarry,g[2],p[2]);
	fullAdder1b a3(X[3],Y[3],genCarry,g[3],p[3]);
	
	lookAhead4b gen1(carryIn, g,p,G,P,genCarry);






















endmodule

Lab3/sourceCode/adder16b.v
module adder16b(X,Y,carryIn,G,P,S);
	input carryIn;
	input [15:0] X;
	input [15:0] Y;
	output G;
	output P;
	output [15:0] S;
	wire [3:0] g;
	wire [3:0] p;
	wire [4:1] c;
	adder4b a0 (X[3:0],  Y[3:0],  carryIn,g[0],p[0],S[3:0]  );
	adder4b a4 (X[7:4],  Y[7:4],  c[1],   g[1],p[1],S[7:4]  );
	adder4b a8 (X[11:8], Y[11:8], c[2],   g[2],p[2],S[11:8] );
	adder4b a12(X[15:12],Y[15:12],c[3],   g[3],p[3],S[15:12]);
	
	lookAhead4b LCU16bit(carryIn, g,p,G,P,c);
endmodule

Lab2/sourceCode/mux2_1.sv
module mux2_1(out, i0, i1, sel);
		output out;
		input i0, i1, sel;
		
		wire out1, out2, NOTsel;
		not n(NOTsel, sel);
		
		and a1(out1, i1, sel);
		and a2(out2, i0, NOTsel);
		or o(out, out1, out2);
endmodule

module mux2_1_testbench();
		reg i0, i1, sel;
		wire out;
		
		mux2_1 dut (.out, .i0, .i1, .sel);
		
		initial begin
				sel = 0; i0 = 0; i1 = 0; #10;
				sel = 0; i0 = 0; i1 = 1; #10;
				sel = 0; i0 = 1; i1 = 0; #10;
				sel = 0; i0 = 1; i1 = 1; #10;
				sel = 1; i0 = 0; i1 = 0; #10;
				sel = 1; i0 = 0; i1 = 1; #10;
				sel = 1; i0 = 1; i1 = 0; #10;
				sel = 1; i0 = 1; i1 = 1; #10;
		end
endmodule

Lab3/sourceCode/adder_subtractor.v
// A - B
module adder_subtractor(S, busA, busB,sel,carryOut);
	input [31:0] busA, busB;
	input sel;
	output [31:0]S;
	output carryOut;
	wire [31:0] selB;
	wire [31:0] notB;
	wire [1:0] g;
	wire [1:0] p;
	wire c;
	
	genvar i;
	generate
		for (i = 0; i < 32; i = i+1) begin: AddorSubtract
			nor n1(notB[i], busB[i]);
			mux2_1 choose1(selB[i], busB[i], notB[i], sel);
		end
	endgenerate
	
	adder16b a0 (busA[15:0], selB[15:0] , sel,g[0],p[0],S[15:0] );
	adder16b a16(busA[31:16],selB[31:16],  c ,g[1],p[1],S[31:16]);
	
	assign c        = sel * p[0] + g[0];
	assign carryOut = c   * p[1] + g[1];

endmodule

Lab3/sourceCode/subtract.v
// active high flags


module subtract (busSUB, busA, busB, zSUB, oSUB, cSUB, nSUB);
	output [31:0] busSUB;
	input  [31:0] busA, busB;
	output zSUB, oSUB, cSUB, nSUB;

	wire carryOut;
	
	adder_subtractor a1(busSUB, busA, busB,1'b1,carryOut);

	flag test(busSUB, busA, busB, carryOut, zSUB, oSUB, cSUB, nSUB);
endmodule

Lab3/sourceCode/setLT.v
// logical set less than
// @requires: Two 32 bit signed 2's complemented, a completed subtract module 
// @returns: (R[rt] = (R[rs] < R[rt])? 32'b1:32'b0), set less than
module setLT (busSLT, busA, busB);
	output [31:0] busSLT;
	input  [31:0] busA, busB;
	wire zADD, oADD, cADD, nADD;

	wire [31:0] busSUB;

	// use sign extension assign busSLT[31:1] = 30'b0;
	subtract sub1(busSUB, busA, busB, zSUB, oSUB, cSUB, nSUB);
	// buf e2(busSLT[0], busSUB[31]);
	assign busSLT[31:0] = {31'b0, busSUB[31]};
endmodule

Lab3/sourceCode/tests/setLTtest.v
`include "adder_subtractor.v"
`include "flag.v"
`include "mux2_1.sv"
`include "adder16b.v"
`include "adder4b.v"
`include "fullAdder1b.v"
`include "lookAhead4b.v"
`include "subtract.v"
`include "setLT.v"
module setLTtest ();
	// localize variables
	wire [31:0] busADD;
	wire  [31:0] busA, busB;

	// declare an instance of the module
	setLT setLT (busADD, busA, busB);
	// Running the GUI part of simulation
	setLTtester tester (busADD, busA, busB);

	// file for gtkwave

	initial
	begin
		$dumpfile("setLTtest.vcd");
		$dumpvars(1, setLT);
	end

endmodule

module setLTtester (busADD, busA, busB);
	input [31:0] busADD;
	output reg  [31:0] busA, busB;

	parameter d = 20;
	initial // Response
	begin
		$display("busADD \t busA \t busB \t\t\t ");
		#d;
	end

	reg [31:0] i;
	initial // Stimulus
	begin
		$monitor("%b \t %b \t %b \t ", busADD, busA, busB, $time);
		// positive + positive
		busA = 32'h01010101; busB = 32'h01010101;
		#d;
		busA = 32'h7FFFFFFF; busB = 32'h7FFFFFFF; // should overflow
		#d;
		// positive + negative
		busA = 32'h01010101; busB = 32'hFFFFFFFF; // 01010101 + -1
		#d;
		busA = 32'h00000001; busB = 32'hF0000000;
		#d;
		// negative + positive
		busA = 32'hFFFFFFFF; busB = 32'h01010101;
		#d;
		busA = 32'hF0000000; busB = 32'h00000001;
		#d;
		// negative + negative 
		busA = 32'hFFFFFFFF; busB = 32'hFFFFFFFF; // -1 + -1
		#d;
		busA = 32'h90000000; busB = 32'h80000000; // should overflow
		#d;
		#(3*d);
		$stop; 
		$finish;
	end

endmodule

Lab3/sourceCode/setLTtest.vcd
$date
	Tue May 05 17:43:04 2015
$end
$version
	Icarus Verilog
$end
$timescale
	1s
$end
$scope module setLTtest $end
$scope module setLT $end
$var wire 32 ! busA [31:0] $end
$var wire 32 " busB [31:0] $end
$var wire 32 # busSLT [31:0] $end
$var wire 32 $ busSUB [31:0] $end
$var wire 1 % cSUB $end
$var wire 1 & nSUB $end
$var wire 1 ' oSUB $end
$var wire 1 ( zSUB $end
$upscope $end
$upscope $end
$enddefinitions $end
#0
$dumpvars
1(
0'
0&
1%
b0 $
b0 #
b1000000010000000100000001 "
b1000000010000000100000001 !
$end
#20
0'
0&
b0 #
1%
1(
b0 $
b1111111111111111111111111111111 "
b1111111111111111111111111111111 !
#40
0%
0(
b1000000010000000100000010 $
b11111111111111111111111111111111 "
b1000000010000000100000001 !
#60
b10000000000000000000000000001 $
b11110000000000000000000000000000 "
b1 !
#80
1%
1&
b1 #
b11111110111111101111111011111110 $
b1000000010000000100000001 "
b11111111111111111111111111111111 !
#100
b11101111111111111111111111111111 $
b1 "
b11110000000000000000000000000000 !
#120
1(
1'
0&
b0 #
b0 $
b11111111111111111111111111111111 "
b11111111111111111111111111111111 !
#140
1'
0&
b0 #
1%
0(
b10000000000000000000000000000 $
b10000000000000000000000000000000 "
b10010000000000000000000000000000 !
