Lab3/sourceCode/xorGate.v
module xorGate (busXOR, busA, busB);
	output [31:0] busXOR;
	input  [31:0] busA, busB;

	genvar i;
	generate
		for (i = 0; i < 32; i = i + 1) begin: xorLoop
			xor gateA(busXOR[i], busA[i], busB[i]);
		end
	endgenerate

endmodule

Lab3/sourceCode/tests/xorGateTest.v
`include "xorGate.v"
module xorGateTest ();
	// localize variables
	wire [31:0] busADD;
	wire  [31:0] busA, busB;

	// declare an instance of the module
	xorGate xorGate (busADD, busA, busB);
	// Running the GUI part of simulation
	xorGatetester tester (busADD, busA, busB);

	// file for gtkwave

	initial
	begin
		$dumpfile("xorGatetest.vcd");
		$dumpvars(1, xorGate);
	end

endmodule

module xorGatetester (busADD, busA, busB);
	input [31:0] busADD;
	output reg  [31:0] busA, busB;

	parameter d = 20;
	initial // Response
	begin
		$display("busADD \t busA \t busB \t\t\t ");
		#d;
	end

	reg [31:0] i;
	initial // Stimulus
	begin
		$monitor("%b \t %b \t %b \t ", busADD, busA, busB, $time);
		// positive + positive
		busA = 32'h01010101; busB = 32'h01010101;
		#d;
		busA = 32'h7FFFFFFF; busB = 32'h7FFFFFFF; // should overflow
		#d;
		// positive + negative
		busA = 32'h01010101; busB = 32'hFFFFFFFF; // 01010101 + -1
		#d;
		busA = 32'h00000001; busB = 32'hF0000000;
		#d;
		// negative + positive
		busA = 32'hFFFFFFFF; busB = 32'h01010101;
		#d;
		busA = 32'hF0000000; busB = 32'h00000001;
		#d;
		// negative + negative 
		busA = 32'hFFFFFFFF; busB = 32'hFFFFFFFF; // -1 + -1
		#d;
		busA = 32'h90000000; busB = 32'h80000000; // should overflow
		#d;
		#(3*d);
		$stop; 
		$finish;
	end

endmodule

Lab3/sourceCode/xorGatetest.vcd
$date
	Tue May 05 17:24:31 2015
$end
$version
	Icarus Verilog
$end
$timescale
	1s
$end
$scope module xorGateTest $end
$scope module xorGate $end
$var wire 32 ! busA [31:0] $end
$var wire 32 " busB [31:0] $end
$var wire 32 # busXOR [31:0] $end
$upscope $end
$upscope $end
$enddefinitions $end
#0
$dumpvars
b0 #
b1000000010000000100000001 "
b1000000010000000100000001 !
$end
#20
b1111111111111111111111111111111 "
b1111111111111111111111111111111 !
#40
b11111110111111101111111011111110 #
b11111111111111111111111111111111 "
b1000000010000000100000001 !
#60
b11110000000000000000000000000001 #
b11110000000000000000000000000000 "
b1 !
#80
b11111110111111101111111011111110 #
b1000000010000000100000001 "
b11111111111111111111111111111111 !
#100
b11110000000000000000000000000001 #
b1 "
b11110000000000000000000000000000 !
#120
b0 #
b11111111111111111111111111111111 "
b11111111111111111111111111111111 !
#140
b10000000000000000000000000000 #
b10000000000000000000000000000000 "
b10010000000000000000000000000000 !
